{
    "blank": {
        "active": false,
        "name": "na",
        "description": "na",
        "time": "na",
        "rewards": "na"
    },

    "raceI": {
        "active": false,
        "name": "Title Race: -Trash Collector-",
        "description": "A race to see who gets the -Trash Collector- title first!",
        "time": "na",
        "rewards": "350 POKEDOLLARS"
    },

    "raceII": {
        "active": false,
        "name": "Title Race: -Sparkly Garbage-",
        "description": "A race to see who gets the -Sparkly Garbage- title!",
        "time": "na",
        "rewards": "500 POKEDOLLARS"
    },

    "raceIII": {
        "active": true,
        "name": "Title Challenge: -Kid's First Art-",
        "description": "A challenge to see who gets the -Kid's First Art- title!",
        "time": "na",
        "rewards": "200 POKEDOLLARS"
    },

    "raceIV": {
        "active": true,
        "name": "Title Challenge: -A Full Fridge-",
        "description": "A challenge to see who gets the -A Full Fridge- title!",
        "time": "na",
        "rewards": "500 POKEDOLLARS"
    },

    "raceV": {
        "active": true,
        "name": "Title Challenge: -A Hidden Card-",
        "description": "A challenge to see who gets the -A Hidden Card- title!",
        "time": "na",
        "rewards": "1000 POKEDOLLARS"
    },

    "affectionI": {
        "active": false,
        "name": "Affection Contest: -006-Jigglypuff-",
        "description": "Raise your affection with a basic Jigglypuff and who ever has the highest at the end of the event wins!",
        "time": "Ends <t:1737918000:R>",
        "rewards": "A refund of all SHARDS and GEMS used to level, +1 level of SHARDS/GEMS, 350 POKEDOLLARS"
    }

    
}